clickhouse2pandas/__init__.py
clickhouse2pandas-0.0.3.dist-info/LICENSE
clickhouse2pandas-0.0.3.dist-info/METADATA
clickhouse2pandas-0.0.3.dist-info/WHEEL
clickhouse2pandas-0.0.3.dist-info/top_level.txt
clickhouse2pandas-0.0.3.dist-info/RECORD
