Metadata-Version: 2.1
Name: clickhouse2pandas
Version: 0.0.3
Summary: Select ClickHouse data, convert to pandas dataframes
Home-page: https://github.com/lee19840806/clickhouse2pandas
Author: Shicheng Li
Author-email: leegao36@163.com
License: UNKNOWN
Project-URL: ClickHouse DB, https://clickhouse.yandex/
Project-URL: Pandas, https://pandas.pydata.org/
Keywords: clickhouse pandas dataframe
Platform: UNKNOWN
Classifier: Development Status :: 3 - Alpha
Classifier: Programming Language :: Python :: 3
Classifier: License :: OSI Approved :: Apache Software License
Classifier: Operating System :: OS Independent
Requires-Python: >=3
Requires-Dist: pandas (>=0.20.0)
